{
    "Jakob_Anna": [
        "Distance",
        0.962918866812832
    ],
    "Anna_Jakob": [
        "Distance",
        0.9629188668128305
    ],
    "Marie_Paul": [
        "Distance",
        0.9400642714273413
    ],
    "Paul_Marie": [
        "Distance",
        0.9400642714273376
    ],
    "Jakob_Maximilian": [
        "Distance",
        0.9185560514008159
    ],
    "Maximilian_Jakob": [
        "Distance",
        0.9185560514008155
    ],
    "Anna_Maximilian": [
        "Distance",
        0.899259305687417
    ],
    "Maximilian_Anna": [
        "Distance",
        0.8992593056874162
    ],
    "Laura_David": [
        "Distance",
        0.7863113963011334
    ],
    "David_Laura": [
        "Distance",
        0.7863113963011334
    ]
}